{
    "Version": "1.2",
    "Data": {
        "Source": "c:\\ndh\\nbc\\myprojectnbc\\source\\myprojectnbc\\myactor.cpp",
        "ProvidedModule": "",
        "PCH": "c:\\ndh\\nbc\\myprojectnbc\\intermediate\\build\\win64\\x64\\myprojectnbceditor\\development\\unrealed\\sharedpch.unrealed.project.valapi.cpp20.h.pch",
        "Includes": [
            "c:\\ndh\\nbc\\myprojectnbc\\intermediate\\build\\win64\\x64\\unrealeditor\\development\\myprojectnbc\\definitions.myprojectnbc.h",
            "c:\\ndh\\nbc\\myprojectnbc\\source\\myprojectnbc\\myactor.h",
            "c:\\ndh\\nbc\\myprojectnbc\\intermediate\\build\\win64\\unrealeditor\\inc\\myprojectnbc\\uht\\myactor.generated.h"
        ],
        "ImportedModules": [],
        "ImportedHeaderUnits": []
    }
}